je_api_testka/__init__.py
je_api_testka/__main__.py
je_api_testka/gui/__init__.py
je_api_testka/gui/api_testka_gui_thread.py
je_api_testka/gui/main_widget.py
je_api_testka/gui/main_window.py
je_api_testka/gui/message_queue.py
je_api_testka/gui/language_wrapper/__init__.py
je_api_testka/gui/language_wrapper/english.py
je_api_testka/gui/language_wrapper/multi_language_wrapper.py
je_api_testka/gui/language_wrapper/traditional_chinese.py
je_api_testka/httpx_wrapper/__init__.py
je_api_testka/httpx_wrapper/async_httpx_method.py
je_api_testka/httpx_wrapper/httpx_data.py
je_api_testka/httpx_wrapper/httpx_method.py
je_api_testka/requests_wrapper/__init__.py
je_api_testka/requests_wrapper/request_method.py
je_api_testka/requests_wrapper/requests_data.py
je_api_testka/utils/__init__.py
je_api_testka/utils/assert_result/__init__.py
je_api_testka/utils/assert_result/result_check.py
je_api_testka/utils/callback/__init__.py
je_api_testka/utils/callback/callback_function_executor.py
je_api_testka/utils/exception/__init__.py
je_api_testka/utils/exception/exception_tags.py
je_api_testka/utils/exception/exceptions.py
je_api_testka/utils/executor/__init__.py
je_api_testka/utils/executor/action_executor.py
je_api_testka/utils/file_process/__init__.py
je_api_testka/utils/file_process/get_dir_file_list.py
je_api_testka/utils/generate_report/__init__.py
je_api_testka/utils/generate_report/html_report_generate.py
je_api_testka/utils/generate_report/json_report.py
je_api_testka/utils/generate_report/xml_report.py
je_api_testka/utils/json/__init__.py
je_api_testka/utils/json/json_file/__init__.py
je_api_testka/utils/json/json_file/json_file.py
je_api_testka/utils/json/json_format/__init__.py
je_api_testka/utils/json/json_format/json_process.py
je_api_testka/utils/logging/__init__.py
je_api_testka/utils/logging/loggin_instance.py
je_api_testka/utils/mock_server/__init__.py
je_api_testka/utils/mock_server/flask_mock_server.py
je_api_testka/utils/package_manager/__init__.py
je_api_testka-0.0.135.dist-info/METADATA
je_api_testka-0.0.135.dist-info/WHEEL
je_api_testka-0.0.135.dist-info/top_level.txt
je_api_testka-0.0.135.dist-info/RECORD
